phasermagic/__init__.py
phasermagic/phasermagic.py
phasermagic-2.8.0.dist-info/METADATA
phasermagic-2.8.0.dist-info/WHEEL
phasermagic-2.8.0.dist-info/top_level.txt
phasermagic-2.8.0.dist-info/RECORD
