Metadata-Version: 2.2
Name: phasermagic
Version: 2.8.0
Summary: This Python package is a magic command that executes Python code in code cells on Jupyter and Google Colab using PyScript and Phaser within an iframe.
Author: Uniras
Author-email: tkappeng@gmail.com
License: MIT License
Project-URL: Homepage, https://github.com/uniras/PhaserMagic
Project-URL: Repository, https://github.com/uniras/PhaserMagic
Keywords: Phaser,jupyter,magic,colab,iframe,pyscript
Classifier: Development Status :: 5 - Production/Stable
Classifier: Intended Audience :: Developers
Classifier: License :: OSI Approved :: MIT License
Classifier: Programming Language :: Python :: 3
Classifier: Programming Language :: Python :: 3.7
Classifier: Programming Language :: Python :: 3.8
Classifier: Programming Language :: Python :: 3.9
Classifier: Programming Language :: Python :: 3.10
Classifier: Programming Language :: Python :: 3.11
Classifier: Programming Language :: Python :: 3.12
Classifier: Programming Language :: Python :: 3.13
Classifier: Programming Language :: Python :: 3 :: Only
Classifier: Topic :: Software Development :: Libraries
Classifier: Topic :: Software Development :: Libraries :: Python Modules
Classifier: Topic :: Utilities
